{"id":"qkk3MGMtlaWgEjRB","title":"Rule 1","vault":{"fsPath":"vault"},"type":"note","desc":"","links":[{"from":{"fname":"ext.deep-work","vaultName":"vault"},"type":"backlink","position":{"start":{"line":6,"column":1,"offset":24},"end":{"line":6,"column":37,"offset":60},"indent":[]},"value":"ext.deep-work.rule-1","alias":"Work Deeply"},{"from":{"fname":"archive.daily.journal.2021.06.29","vaultName":"vault"},"type":"backlink","position":{"start":{"line":13,"column":1,"offset":413},"end":{"line":13,"column":25,"offset":437},"indent":[]},"value":"ext.deep-work.rule-1","alias":"ext.deep-work.rule-1"},{"from":{"fname":"archive.daily.journal.2021.06.29","vaultName":"vault"},"type":"backlink","position":{"start":{"line":17,"column":9,"offset":526},"end":{"line":17,"column":52,"offset":569},"indent":[]},"value":"ext.deep-work.rule-1","alias":"Monastic"},{"from":{"fname":"archive.daily.journal.2021.06.29","vaultName":"vault"},"type":"backlink","position":{"start":{"line":18,"column":9,"offset":627},"end":{"line":18,"column":51,"offset":669},"indent":[]},"value":"ext.deep-work.rule-1","alias":"Bimodal"},{"from":{"fname":"archive.daily.journal.2021.06.29","vaultName":"vault"},"type":"backlink","position":{"start":{"line":21,"column":15,"offset":948},"end":{"line":21,"column":73,"offset":1006},"indent":[]},"value":"ext.deep-work.rule-1","alias":"my willpower is limited"},{"from":{"fname":"archive.daily.journal.2021.06.29","vaultName":"vault"},"type":"backlink","position":{"start":{"line":23,"column":9,"offset":1341},"end":{"line":23,"column":52,"offset":1384},"indent":[]},"value":"ext.deep-work.rule-1","alias":"Rhythmic"},{"from":{"fname":"archive.daily.journal.2021.06.29","vaultName":"vault"},"type":"backlink","position":{"start":{"line":24,"column":33,"offset":1486},"end":{"line":24,"column":80,"offset":1533},"indent":[]},"value":"ext.deep-work.rule-1","alias":"Journalistic"},{"from":{"fname":"archive.daily.journal.2021.06.30","vaultName":"vault"},"type":"backlink","position":{"start":{"line":2,"column":1,"offset":1},"end":{"line":2,"column":25,"offset":25},"indent":[]},"value":"ext.deep-work.rule-1","alias":"ext.deep-work.rule-1"},{"from":{"fname":"archive.daily.journal.2021.07.20","vaultName":"vault"},"type":"backlink","position":{"start":{"line":12,"column":42,"offset":681},"end":{"line":12,"column":98,"offset":737},"indent":[]},"value":"ext.deep-work.rule-1","alias":"shutting down"}],"anchors":{"rule-1":{"type":"header","value":"rule-1","line":8,"column":0},"eudaimonia-machine":{"type":"header","value":"eudaimonia-machine","line":12,"column":0},"simply-reminding-yourself-to-concentrate-more-isnt-enough-for-deep-work":{"type":"header","value":"simply-reminding-yourself-to-concentrate-more-isnt-enough-for-deep-work","line":19,"column":0},"strategies":{"type":"header","value":"strategies","line":24,"column":0},"decide-on-your-depth-philosophy":{"type":"header","value":"decide-on-your-depth-philosophy","line":26,"column":0},"ritualize":{"type":"header","value":"ritualize","line":56,"column":0},"make-grand-gestures":{"type":"header","value":"make-grand-gestures","line":79,"column":0},"dont-work-alone":{"type":"header","value":"dont-work-alone","line":91,"column":0},"execute-like-a-business":{"type":"header","value":"execute-like-a-business","line":100,"column":0},"be-lazy":{"type":"header","value":"be-lazy","line":127,"column":0},"^Y0Ql_XBV":{"type":"block","value":"Y0Ql_XBV","line":21,"column":79},"^Fop4AVPo":{"type":"block","value":"Fop4AVPo","line":31,"column":16},"^2zHHwu66":{"type":"block","value":"2zHHwu66","line":36,"column":15},"^Gqkgruf8":{"type":"block","value":"Gqkgruf8","line":41,"column":16},"^tdNLbh_j":{"type":"block","value":"tdNLbh_j","line":50,"column":20},"^2bdoDu3q":{"type":"block","value":"2bdoDu3q","line":62,"column":74},"^HnqIEqCAMwE8MZ92":{"type":"block","value":"HnqIEqCAMwE8MZ92","line":131,"column":34}},"fname":"ext.deep-work.rule-1","updated":1625041691136,"created":1624712840787,"parent":"GubAN8JRkCVLNRBsX_5e4","children":[],"data":{},"contentHash":"951a25fdb0e5bd124da78a145b18ddcc","custom":{}}
